{"asenders": 39, "asenders_30": 0, "asenders_365": 35, "asenders_7": 0, "asent": 40, "asent_30": 0, "asent_365": 36, "asent_7": 0, "csenders": 23, "csenders_30": 0, "csenders_365": 21, "csenders_7": 0, "csent": 34, "csent_30": 0, "csent_365": 30, "csent_7": 0, "diff_netasenders_30": -3, "diff_netasenders_365": 31, "diff_netasenders_7": 0, "diff_netasent_30": -3, "diff_netasent_365": 32, "diff_netasent_7": 0, "diff_netcsenders_30": 0, "diff_netcsenders_365": 19, "diff_netcsenders_7": 0, "diff_netcsent_30": 0, "diff_netcsent_365": 26, "diff_netcsent_7": 0, "diff_netparticipants_30": -24, "diff_netparticipants_365": 1747, "diff_netparticipants_7": -29, "diff_netqsenders_30": -1, "diff_netqsenders_365": 18, "diff_netqsenders_7": 0, "diff_netqsent_30": -1, "diff_netqsent_365": 27, "diff_netqsent_7": 0, "first_date": "2010-07-21", "last_date": "2014-07-09", "participants": 4586, "participants_30": 409, "participants_365": 2989, "participants_7": 110, "percentage_asenders_30": 100, "percentage_asenders_365": 775, "percentage_asenders_7": 0, "percentage_asent_30": 100, "percentage_asent_365": 800, "percentage_asent_7": 0, "percentage_csenders_30": 0, "percentage_csenders_365": 950, "percentage_csenders_7": 0, "percentage_csent_30": 0, "percentage_csent_365": 650, "percentage_csent_7": 0, "percentage_participants_30": 5, "percentage_participants_365": 140, "percentage_participants_7": 20, "percentage_qsenders_30": 100, "percentage_qsenders_365": 450, "percentage_qsenders_7": 0, "percentage_qsent_30": 100, "percentage_qsent_365": 675, "percentage_qsent_7": 0, "qsenders": 26, "qsenders_30": 0, "qsenders_365": 22, "qsenders_7": 0, "qsent": 35, "qsent_30": 0, "qsent_365": 31, "qsent_7": 0}