{"senders.":{"senders":["sumanah","codurr","MatmaRex","Reedy","Krinkle","hashar","marktraceur","Dantman","","^demon"],"sent":[28078,15874,15454,15268,11844,9608,9411,8115,7744,7458]},"senders.last year":{"senders":["MatmaRex","sumanah","marktraceur","Reedy","Susan","Isarra","YuviPanda","Brooke","","bawolff"],"sent":[15454,13440,8395,6294,5349,4998,4747,4507,4397,4179]},"senders.last month":{"senders":["rickyb98","YuviPanda","MatmaRex","marktraceur","bawolff","Elsie","Reedy","spstarr_work","","ori-l"],"sent":[1099,990,889,768,604,455,347,325,317,299]}}