{"closers.":{"id":[4,47,6886,51,2187,6,3991,583,10,1453],"closers":["Brion Vibber","Rob Church","roan.kattouw","Werdna","innocentkiller@gmail.com","Roan Kattouw","markusd112@web.de","brion","Antoine Musso","Alkivar@yahoo.com"],"closed":[3305,1743,994,945,904,883,800,766,763,758]},"closers.last year":{"id":[7233,1453,59,60,6910,7401,4390,214,6928,5006],"closers":["denny.vrandecic","Alkivar@yahoo.com","Matthias Mullie","Alex Monk","aklapper","jeroen_dedauw","duplicatebug@googlemail.com","mwjames","federicoleva","szaydel@pacbell.net"],"closed":[534,473,317,273,233,187,175,174,170,166]},"closers.last month":{"id":[1453,6910,6928,265,214,27,68,60,6912,59],"closers":["Alkivar@yahoo.com","aklapper","federicoleva","bsitu","mwjames","Matthew Flaschen","Arthur Richards","Alex Monk","matma.rex","Matthias Mullie"],"closed":[49,36,24,18,18,14,13,13,12,12]}}