{"actions": 52643, "added_lines": 1451100.0, "added_lines_30": 368452, "added_lines_365": 9921369, "added_lines_7": 29810, "authors": 7, "authors_30": 3, "authors_365": 5, "authors_7": 1, "avg_commits_author": 972.86, "avg_commits_month": 219.68, "avg_files_author": 2203.0, "avg_files_month": 497.45, "branches": 8, "commits": 6810, "commits_30": 251, "commits_365": 2805, "commits_7": 2, "committers": 7, "diff_netadded_lines_30": -666014, "diff_netadded_lines_365": -3973599, "diff_netadded_lines_7": -80805, "diff_netauthors_30": 0, "diff_netauthors_365": -1, "diff_netauthors_7": -1, "diff_netcommits_30": 10, "diff_netcommits_365": 291, "diff_netcommits_7": -73, "diff_netfiles_30": 377, "diff_netfiles_365": 2646, "diff_netfiles_7": -182, "diff_netremoved_lines_30": -1234963, "diff_netremoved_lines_365": -4768296, "diff_netremoved_lines_7": -59329, "files": 15421, "files_30": 1414, "files_365": 11328, "files_7": 2, "first_date": "2006-04-03", "last_date": "2014-11-28", "percentage_added_lines_30": 64, "percentage_added_lines_365": 28, "percentage_added_lines_7": 73, "percentage_authors_30": 0, "percentage_authors_365": 16, "percentage_authors_7": 50, "percentage_commits_30": 4, "percentage_commits_365": 11, "percentage_commits_7": 97, "percentage_files_30": 36, "percentage_files_365": 30, "percentage_files_7": 98, "percentage_removed_lines_30": 82, "percentage_removed_lines_365": 36, "percentage_removed_lines_7": 79, "removed_lines": 788168.0, "removed_lines_30": 253915, "removed_lines_365": 8306653, "removed_lines_7": 15408, "repositories": 1}