{"asenders": 116, "asenders_30": 27, "asenders_365": 116, "asenders_7": 6, "asent": 163, "asent_30": 32, "asent_365": 163, "asent_7": 6, "csenders": 73, "csenders_30": 20, "csenders_365": 73, "csenders_7": 11, "csent": 153, "csent_30": 34, "csent_365": 153, "csent_7": 17, "diff_netasenders_30": 17, "diff_netasenders_365": 116, "diff_netasenders_7": -3, "diff_netasent_30": 19, "diff_netasent_365": 163, "diff_netasent_7": -3, "diff_netcsenders_30": 9, "diff_netcsenders_365": 73, "diff_netcsenders_7": 7, "diff_netcsent_30": 16, "diff_netcsent_365": 153, "diff_netcsent_7": 12, "diff_netparticipants_30": -11, "diff_netparticipants_365": 1785, "diff_netparticipants_7": -31, "diff_netqsenders_30": 18, "diff_netqsenders_365": 144, "diff_netqsenders_7": 1, "diff_netqsent_30": 20, "diff_netqsent_365": 169, "diff_netqsent_7": 1, "init_date": "2010-07-21", "last_date": "2014-06-14", "participants": 4412, "participants_30": 420, "participants_365": 2926, "participants_7": 118, "percentage_asenders_30": 170, "percentage_asenders_365": 0, "percentage_asenders_7": 33, "percentage_asent_30": 146, "percentage_asent_365": 0, "percentage_asent_7": 33, "percentage_csenders_30": 81, "percentage_csenders_365": 0, "percentage_csenders_7": 175, "percentage_csent_30": 88, "percentage_csent_365": 0, "percentage_csent_7": 240, "percentage_participants_30": 2, "percentage_participants_365": 156, "percentage_participants_7": 20, "percentage_qsenders_30": 163, "percentage_qsenders_365": 0, "percentage_qsenders_7": 14, "percentage_qsent_30": 181, "percentage_qsent_365": 0, "percentage_qsent_7": 14, "qsenders": 144, "qsenders_30": 29, "qsenders_365": 144, "qsenders_7": 8, "qsent": 169, "qsent_30": 31, "qsent_365": 169, "qsent_7": 8}