{"abandoned": 128, "abandoned_30": 2, "abandoned_365": 111, "abandoned_7": 0, "closed": 736, "closed_30": 6, "closed_365": 656, "closed_7": 1, "diff_netabandoned_30": 2, "diff_netabandoned_365": 95, "diff_netabandoned_7": 0, "diff_netclosed_30": -19, "diff_netclosed_365": 581, "diff_netclosed_7": 0, "diff_netmerged_30": -21, "diff_netmerged_365": 486, "diff_netmerged_7": 0, "diff_netpending_30": 11, "diff_netpending_365": 44, "diff_netpending_7": -2, "diff_netsubmitted_30": -8, "diff_netsubmitted_365": 625, "diff_netsubmitted_7": -2, "diff_netsubmitters_30": 0, "diff_netsubmitters_365": 2, "diff_netsubmitters_7": 0, "merged": 608, "merged_30": 4, "merged_365": 545, "merged_7": 1, "pending": 44, "pending_30": 20, "pending_365": 44, "pending_7": 3, "percentage_abandoned_30": 0, "percentage_abandoned_365": 593, "percentage_abandoned_7": 0, "percentage_closed_30": 76, "percentage_closed_365": 774, "percentage_closed_7": 0, "percentage_merged_30": 84, "percentage_merged_365": 823, "percentage_merged_7": 0, "percentage_pending_30": 122, "percentage_pending_365": 0, "percentage_pending_7": 40, "percentage_submitted_30": 23, "percentage_submitted_365": 833, "percentage_submitted_7": 33, "percentage_submitters_30": 0, "percentage_submitters_365": 200, "percentage_submitters_7": 0, "submitted": 780, "submitted_30": 26, "submitted_365": 700, "submitted_7": 4, "submitters": 3, "submitters_30": 1, "submitters_365": 3, "submitters_7": 1}