{"abandoned": 3180, "abandoned_30": 40, "abandoned_365": 1726, "abandoned_7": 8, "closed": 12970, "closed_30": 131, "closed_365": 5313, "closed_7": 13, "diff_netabandoned_30": 4, "diff_netabandoned_365": 842, "diff_netabandoned_7": 2, "diff_netclosed_30": -87, "diff_netclosed_365": 392, "diff_netclosed_7": -15, "diff_netmerged_30": -91, "diff_netmerged_365": -450, "diff_netmerged_7": -17, "diff_netpending_30": 164, "diff_netpending_365": 619, "diff_netpending_7": -5, "diff_netsubmitted_30": 77, "diff_netsubmitted_365": 1011, "diff_netsubmitted_7": -20, "diff_netsubmitters_30": 18, "diff_netsubmitters_365": 169, "diff_netsubmitters_7": 4, "merged": 9790, "merged_30": 91, "merged_365": 3587, "merged_7": 5, "pending": 621, "pending_30": 284, "pending_365": 620, "pending_7": 83, "percentage_abandoned_30": 11, "percentage_abandoned_365": 95, "percentage_abandoned_7": 33, "percentage_closed_30": 39, "percentage_closed_365": 7, "percentage_closed_7": 53, "percentage_merged_30": 50, "percentage_merged_365": 11, "percentage_merged_7": 77, "percentage_pending_30": 136, "percentage_pending_365": 61900, "percentage_pending_7": 5, "percentage_submitted_30": 22, "percentage_submitted_365": 20, "percentage_submitted_7": 17, "percentage_submitters_30": 15, "percentage_submitters_365": 40, "percentage_submitters_7": 7, "submitted": 13591, "submitted_30": 415, "submitted_365": 5933, "submitted_7": 96, "submitters": 876, "submitters_30": 134, "submitters_365": 588, "submitters_7": 60}