{"diff_netsenders_30": 0, "diff_netsenders_365": -1, "diff_netsenders_7": -1, "diff_netsent_30": -1, "diff_netsent_365": -18, "diff_netsent_7": -3, "first_date": "2010-11-11", "last_date": "2014-07-08", "percentage_senders_30": 0, "percentage_senders_365": 33, "percentage_senders_7": 100, "percentage_sent_30": 14, "percentage_sent_365": 23, "percentage_sent_7": 100, "repositories": 6, "senders": 3, "senders_30": 1, "senders_365": 2, "senders_7": 0, "senders_init": 3, "senders_response": 3, "sent": 143, "sent_30": 6, "sent_365": 60, "sent_7": 0, "sent_response": 114, "threads": 114}